feedbackgpt.py
feedbackgpt-0.0.1.dist-info/LICENSE
feedbackgpt-0.0.1.dist-info/METADATA
feedbackgpt-0.0.1.dist-info/WHEEL
feedbackgpt-0.0.1.dist-info/top_level.txt
feedbackgpt-0.0.1.dist-info/RECORD
